allagash/__init__.py
allagash/coverage.py
allagash/problem.py
Allagash-0.4.3.dist-info/LICENSE
Allagash-0.4.3.dist-info/METADATA
Allagash-0.4.3.dist-info/WHEEL
Allagash-0.4.3.dist-info/top_level.txt
Allagash-0.4.3.dist-info/RECORD
