Metadata-Version: 2.1
Name: Allagash
Version: 0.4.3
Summary: A Python Spatial Optimization Library
Author-email: Aaron Pulver <apulverizer@gmail.com>
License: MIT
Project-URL: Homepage, https://apulverizer.github.io/allagash
Project-URL: Bug Tracker, https://github.com/apulverizer/allagash/issues
Classifier: Intended Audience :: Science/Research
Classifier: Programming Language :: Python :: 3
Requires-Python: >=3.6
License-File: LICENSE
Requires-Dist: pandas (>=0.23.0)
Requires-Dist: pulp (>=1.6.1)
Provides-Extra: arcgis
Requires-Dist: arcgis (>=1.8.2) ; extra == 'arcgis'
Provides-Extra: geopandas
Requires-Dist: geopandas (>=0.4.1) ; extra == 'geopandas'
